{
    "tfcFiles":  [
                     {
                         "fullFileName":  "CharTextures-a_WOTC_AlienPack_DLCTFC_XPACK_.tfc",
                         "originalSize":  65952863,
                         "lastUpdatedUtc":  638256161048208190
                     },
                     {
                         "fullFileName":  "CharTextures_WOTC_AlienPack_DLCTFC_XPACK_.tfc",
                         "originalSize":  13219864,
                         "lastUpdatedUtc":  638256161938265188
                     },
                     {
                         "fullFileName":  "Textures-a_WOTC_AlienPack_DLCTFC_XPACK_.tfc",
                         "originalSize":  891142,
                         "lastUpdatedUtc":  638256161148444961
                     },
                     {
                         "fullFileName":  "Textures_WOTC_AlienPack_DLCTFC_XPACK_.tfc",
                         "originalSize":  5917254,
                         "lastUpdatedUtc":  638256157631853834
                     },
                     {
                         "fullFileName":  "World_WOTC_AlienPack_DLCTFC_XPACK_.tfc",
                         "originalSize":  1557344,
                         "lastUpdatedUtc":  638256161149220198
                     }
                 ],
    "sfPackages":  [
                       {
                           "fullFileName":  "AdvDroneMatinee_SF.upk",
                           "lastUpdatedUtc":  638256157578663254
                       },
                       {
                           "fullFileName":  "AdvGrenadeLauncher_SF.upk",
                           "lastUpdatedUtc":  638256157653307177
                       },
                       {
                           "fullFileName":  "LW_Perk_MutonM3_SF.upk",
                           "lastUpdatedUtc":  638256161381791382
                       },
                       {
                           "fullFileName":  "LW_Perk_Psi_MassMindspin_SF.upk",
                           "lastUpdatedUtc":  638256161489539603
                       },
                       {
                           "fullFileName":  "LW_Perk_Psi_MassReanimation_SF.upk",
                           "lastUpdatedUtc":  638256161581544156
                       },
                       {
                           "fullFileName":  "LW_Perk_RepairServos_SF.upk",
                           "lastUpdatedUtc":  638256161621566952
                       },
                       {
                           "fullFileName":  "LW_Perk_PCS_DamageControl_SF.upk",
                           "lastUpdatedUtc":  638256161417189796
                       },
                       {
                           "fullFileName":  "LW_Perk_CloseCombatSpecialist_SF.upk",
                           "lastUpdatedUtc":  638256161336314745
                       },
                       {
                           "fullFileName":  "LWAdvGrenadier_SF.upk",
                           "lastUpdatedUtc":  638256158095702441
                       },
                       {
                           "fullFileName":  "LWAdvGunner_SF.upk",
                           "lastUpdatedUtc":  638256158647507554
                       },
                       {
                           "fullFileName":  "LWAdvMec_SF.upk",
                           "lastUpdatedUtc":  638256158712295493
                       },
                       {
                           "fullFileName":  "LWAdvMecArcher_SF.upk",
                           "lastUpdatedUtc":  638256158839480579
                       },
                       {
                           "fullFileName":  "LWAdvRocketeer_SF.upk",
                           "lastUpdatedUtc":  638256159225168019
                       },
                       {
                           "fullFileName":  "LWAdvSentry_SF.upk",
                           "lastUpdatedUtc":  638256159614375141
                       },
                       {
                           "fullFileName":  "LWDrone_SF.upk",
                           "lastUpdatedUtc":  638256159780764286
                       },
                       {
                           "fullFileName":  "LWDroneWeapon_SF.upk",
                           "lastUpdatedUtc":  638256160018263051
                       },
                       {
                           "fullFileName":  "LWHiveQueen_SF.upk",
                           "lastUpdatedUtc":  638256160240259186
                       },
                       {
                           "fullFileName":  "LWMutonM2_SF.upk",
                           "lastUpdatedUtc":  638256160354841991
                       },
                       {
                           "fullFileName":  "LWMutonM3_SF.upk",
                           "lastUpdatedUtc":  638256160442766464
                       },
                       {
                           "fullFileName":  "LWMutonM3Rifle_SF.upk",
                           "lastUpdatedUtc":  638256160663796363
                       },
                       {
                           "fullFileName":  "LWNaja_SF.upk",
                           "lastUpdatedUtc":  638256160760010075
                       },
                       {
                           "fullFileName":  "LWSectoidM2_SF.upk",
                           "lastUpdatedUtc":  638256160995591681
                       },
                       {
                           "fullFileName":  "LWSidewinder_SF.upk",
                           "lastUpdatedUtc":  638256161091135093
                       },
                       {
                           "fullFileName":  "LWSidewinderSMG_SF.upk",
                           "lastUpdatedUtc":  638256161296696550
                       },
                       {
                           "fullFileName":  "NajaRifle_SF.upk",
                           "lastUpdatedUtc":  638256161821053191
                       },
                       {
                           "fullFileName":  "UILibrary_LWAlienPack_SF.upk",
                           "lastUpdatedUtc":  638256161859472072
                       },
                       {
                           "fullFileName":  "XAdventTrooper_SF.upk",
                           "lastUpdatedUtc":  638256162259731118
                       }
                   ]
}
